pyShodan/__init__.py
pyShodan/test.py
pyShodan-0.2.16.dist-info/LICENSE
pyShodan-0.2.16.dist-info/METADATA
pyShodan-0.2.16.dist-info/WHEEL
pyShodan-0.2.16.dist-info/top_level.txt
pyShodan-0.2.16.dist-info/RECORD
