Metadata-Version: 2.1
Name: pyShodan
Version: 0.2.16
Summary: Python library for querying the Shodan API
Home-page: https://github.com/Hackman238/pyShodan
Author: Shane Scott
Author-email: gs@shanewilliamscott.com
Classifier: Development Status :: 4 - Beta
Classifier: Intended Audience :: Developers
Classifier: License :: OSI Approved :: GNU General Public License v3 (GPLv3)
Classifier: Programming Language :: Python :: 3.6
Classifier: Programming Language :: Python :: 3.7
Classifier: Programming Language :: Python :: 3.8
Classifier: Programming Language :: Python :: 3.9
Classifier: Programming Language :: Python :: 3.10
Classifier: Programming Language :: Python :: 3.11
Classifier: Operating System :: OS Independent
License-File: LICENSE
Requires-Dist: shodan
Requires-Dist: IPy
